nekosrewrite/__init__.py
nekosrewrite/nekosrewrite.py
nekosrewrite-1.0.3.dist-info/LICENSE
nekosrewrite-1.0.3.dist-info/METADATA
nekosrewrite-1.0.3.dist-info/WHEEL
nekosrewrite-1.0.3.dist-info/top_level.txt
nekosrewrite-1.0.3.dist-info/RECORD
